watcher/__init__.py
watcher/auth.py
watcher/client.py
watcher/exceptions.py
watcher/http_client.py
watcher/models/address_lineage.py
watcher/models/execution.py
watcher/models/pipeline.py
watcher/orchestration.py
watcher/types.py
etl_watcher_sdk-0.1.43.dist-info/WHEEL
etl_watcher_sdk-0.1.43.dist-info/METADATA
etl_watcher_sdk-0.1.43.dist-info/RECORD
