Metadata-Version: 2.4
Name: etl-watcher-sdk
Version: 0.1.43
Summary: SDK for Watcher framework
License-Expression: MIT
Classifier: Programming Language :: Python :: 3
Classifier: Operating System :: OS Independent
Requires-Dist: httpx[http2]>=0.28.1
Requires-Dist: pydantic>=2.12.0
Requires-Dist: pydantic-extra-types[pendulum]>=2.10.6
Requires-Dist: pytest-xdist>=3.8.0
Requires-Dist: boto3>=1.26.0 ; extra == 'aws'
Requires-Dist: azure-identity>=1.0.0 ; extra == 'azure'
Requires-Dist: twine>=6.2.0 ; extra == 'build'
Requires-Dist: uv-build>=0.9.0 ; extra == 'build'
Requires-Dist: google-auth>=2.0.0 ; extra == 'cloud'
Requires-Dist: azure-identity>=1.0.0 ; extra == 'cloud'
Requires-Dist: boto3>=1.26.0 ; extra == 'cloud'
Requires-Dist: pytest>=8.4.2 ; extra == 'dev'
Requires-Dist: ruff>=0.14.0 ; extra == 'dev'
Requires-Dist: pre-commit>=4.3.0 ; extra == 'dev'
Requires-Dist: myst-parser>=4.0.1 ; extra == 'docs'
Requires-Dist: sphinx>=8.2.3 ; extra == 'docs'
Requires-Dist: sphinx-autobuild>=2025.8.25 ; extra == 'docs'
Requires-Dist: sphinx-autodoc-typehints>=3.2.0 ; extra == 'docs'
Requires-Dist: sphinx-rtd-theme>=3.0.2 ; extra == 'docs'
Requires-Dist: sphinx-tabs>=3.4.7 ; extra == 'docs'
Requires-Dist: sphinxcontrib-httpdomain>=1.8.1 ; extra == 'docs'
Requires-Dist: google-auth>=2.0.0 ; extra == 'gcp'
Requires-Python: >=3.12
Project-URL: Documentation, https://etl-watcher-sdk.readthedocs.io/en/latest/
Project-URL: Homepage, https://github.com/cmgoffena13/etl-watcher-sdk
Provides-Extra: aws
Provides-Extra: azure
Provides-Extra: build
Provides-Extra: cloud
Provides-Extra: dev
Provides-Extra: docs
Provides-Extra: gcp
